
{
  "bg": "https://i.pinimg.com/originals/b4/9f/2e/b49f2e5a263955fdb0484e3cda3fd47f.jpg",
  "title": "Mulher-Maravilha",
  "description": "Teste os seus conhecimentos sobre a Mulher Maravilha",
  "questions": [
    {
      "image": "https://www.hypeness.com.br/1/2019/12/gal-gadot4.gif",
      "title": "Qual é a espécie da Mulher Maravilha?",
      "description": "Essa é pra aquecer",
      "answer": 2,
      "alternatives": [
        ".elemento",
        "*elemento",
        "#elemento",
        "%elemento"
      ]
    },
    {
      "image": "https://data.whicdn.com/images/251383815/original.gif",
      "title": "Em qual hq teve a primeira aparição da Mulher Maravilha?",
      "description": "Faz tempo em haha",
      "answer": 0,
      "alternatives": [
         "background: linear-gradient(#e66465, #9198e5);",
         "background: gradient(#e66465, #9198e5);"
      ]
    }
  ],
  "external": [
    ""
  ],
  "theme": {
    "colors": {
      "primary": "#a73a38",
      "secondary": "#3f51b5",
      "mainBg": "#171B35",
      "contrastText": "#FFFFFF",
      "wrong": "#FF5722",
      "success": "#4CAF50"
    },
    "borderRadius": "4px"
  }
}